<?xml version="1.0" encoding="UTF-8"?>
<!DOCTYPE sect1 PUBLIC "-//OASIS//DTD DocBook XML V4.3//EN"
                       "http://www.docbook.org/xml/4.3/docbookx.dtd">
<!-- section history:
  2007-06-20 Added Spanish translation by AntI
  2007-03-12 Kolbjørn: added no translation
  2005/11/20 reviewed; de created by axel.wernicke
-->
<!--2009-06-30-->
<sect1 xmlns:xi="http://www.w3.org/2001/XInclude" id="gimp-tools-menu">
  <title lang="en">The <quote>Tools</quote> Menu</title>
  <title lang="ja"><quote>ツール(T)</quote>メニュー</title>

  <indexterm lang="en">
    <primary>Menus</primary>
    <secondary>Tools</secondary>
  </indexterm>
  <indexterm lang="ja">
    <primary>メニュー</primary>
    <secondary>ツール</secondary>
  </indexterm>

  <sect2 id="gimp-tools-menu-introduction">
    <title lang="en">Introduction to the <quote>Tools</quote> Menu</title>
    <title lang="ja"><quote>ツール</quote>メニューのあらまし</title>

    <figure>
      <title lang="en">Contents of the <quote>Tools</quote> menu</title>
      <title lang="ja"><quote>ツール</quote>メニューの目次</title>
      <mediaobject>
        <imageobject>
          <imagedata fileref="images/menus/tools.png" format="PNG"/>
        </imageobject>
      </mediaobject>
    </figure>
    <para lang="en">
      The menu entries on the <guimenu>Tools</guimenu> menu access the
      <acronym>GIMP</acronym> tools. All of the tools available in
      <acronym>GIMP</acronym> are extensively described in the
      <link linkend="gimp-toolbox">Toolbox</link> section.
    </para>
    <para lang="ja">
      <guimenu>ツール(<accel>T</accel>)</guimenu> メニューには
      <acronym>GIMP</acronym>の各ツールを呼び出すコマンドが入っています。 
      これら全てのツールについて個別の詳しい説明が 
      <link linkend="gimp-toolbox">ツールボックス</link> の章にあります。
    </para>
  </sect2>
</sect1>
