<?xml version="1.0" encoding="UTF-8"?>
<!DOCTYPE sect2 PUBLIC "-//OASIS//DTD DocBook XML V4.3//EN"
                       "http://www.docbook.org/xml/4.3/docbookx.dtd">
<!-- section history:
  2007-06-13 Added Spanish translation by AntI
  2007-03-12 Kolbjorn: added no translation
  2005/11/16 split of from layer-transparency.xml by axel.wernicke
-->
<!--2012-03-08-->
<sect2 id="plug-in-threshold-alpha">
  <title lang="en">Threshold Alpha</title>
  <title lang="ja">アルファチャンネルしきい値...</title>

  <indexterm lang="en">
    <primary>Layer</primary>
    <secondary>Transparency managing</secondary>
    <tertiary>Threshold</tertiary>
  </indexterm>
  <indexterm lang="en">
    <primary>Alpha</primary>
  </indexterm>
  <indexterm lang="ja">
    <primary>レイヤー</primary>
    <secondary sortas="トウカコウカノカンリ">透過効果の管理</secondary>
    <tertiary sortas="シキイチ">しきい値</tertiary>
  </indexterm>
  <indexterm lang="ja">
    <primary>アルファ</primary>
  </indexterm>

  <para lang="en">
    The <guimenuitem>Threshold Alpha</guimenuitem> command converts
    semi-transparent areas of the active layer into completely transparent or
    completely opaque areas, based on a threshold you set, between 0 and
    255. It only works on layers of RGB images which have an alpha
    channel. If the image is Grayscale or Indexed, or if the layer does not
    have an alpha channel, the menu entry is insensitive and grayed out.
    If the <guilabel>Keep transparency</guilabel> option is checked in the
    Layers dialog, the command displays an error message.
  </para>
  <para lang="ja">
    <guimenuitem>アルファチャンネルしきい値...</guimenuitem>
    コマンドは活性レイヤーの半透明な部分を透過度のしきい値に従い完全透明と
    不完全透明の部分に分けます。 しきい値は 0 から 255 の範囲で任意に
    設定できます。 このコマンドが利用できるのはアルファチャンネルつきの
    <acronym>RGB</acronym>画像に限られます。 グレースケール画像や
    インデックス化カラー画像とアルファチャンネルのない<acronym>RGB</acronym>
    画像の場合はこのコマンドのメニュー項目は灰色無効となっていて使用できません。 
    レイヤーダイアログの <guilabel>透明保護</guilabel> オプションが有効に
    なっているときは透明度が変更できないためエラー報告が出ます。
  </para>

  <sect3>
    <title lang="en">Activating the Command</title>
    <title lang="ja">コマンドの呼び出し方</title>
    <itemizedlist>
      <listitem>
        <para lang="en">
          You can access this command from the image menubar through
          <menuchoice>
            <guimenu>Layer</guimenu>
            <guisubmenu>Transparency</guisubmenu>
            <guimenuitem>Threshold Alpha</guimenuitem>
          </menuchoice>.
        </para>
        <para lang="ja">
          画像ウィンドウのメニューより
          <menuchoice>
            <guimenu>レイヤー</guimenu>
            <guisubmenu>透明部分</guisubmenu>
            <guimenuitem>アルファチャンネルしきい値...</guimenuitem>
          </menuchoice>
        </para>
      </listitem>
    </itemizedlist>
  </sect3>

  <sect3>
    <title lang="en">Description of the Dialog Window</title>
    <title lang="ja">ダイアログウィンドウのご説明</title>
    <figure>
      <title lang="en">
        The only one option of the <quote>Threshold Alpha</quote> dialog
      </title>
      <title lang="ja">
        <quote>アルファチャンネルを 2 階調化</quote>ダイアログの唯一のオプション
      </title>
      <mediaobject>
        <imageobject>
          <imagedata fileref="images/menus/layer/threshold-alpha.png"
            format="PNG"/>
        </imageobject>
      </mediaobject>
    </figure>
    <variablelist>
      <varlistentry>
        <term lang="en">Threshold</term>
        <term lang="ja">しきい値</term>
        <listitem>
          <para lang="en">
            You can set the transparency value to be used as a threshold by
            using the slider or by entering a value between 0 and 255 in
            the input box. All transparency values above this threshold will
            become opaque and all transparency values below or equal to this
            threshold will become completely transparent. The transition is
            abrupt.
          </para>
          <para lang="ja">
            このスライダーや数値記入欄を用いて 0 から 255 の範囲で透明度の
            しきい値を設定できます。 透明度がこのしきい値を上回る領域は
            完全不透明になり、 しきい値以下の透明度の領域は完全透過します。 
            滑らかに変化していた透明度がぎくしゃくしたものになります。
          </para>
          <note>
            <para lang="en">
              This command will never make completely transparent pixels
              (alpha value = 0) opaque.
            </para>
            <para lang="ja">
              このコマンドは完全透明な (アルファ値が 0 の) 画素を不透明化
              できません。
            </para>
          </note>
          <figure>
            <title lang="en">Threshold Alpha example</title>
            <title lang="ja">アルファチャンネル 2 階調化の例</title>
            <mediaobject>
              <imageobject>
                <imagedata format="PNG"
                  fileref="images/menus/layer/threshold-alpha-example.png" />
              </imageobject>
              <caption>
                <para lang="en">A transparency gradient 0-255.</para>
                <para lang="en">0-255 の透明度グラデーション</para>
              </caption>
            </mediaobject>
            <mediaobject>
              <imageobject>
                <imagedata format="PNG"
                  fileref="images/menus/layer/threshold-alpha-example3.png" />
              </imageobject>
              <caption>
                <para lang="en">Threshold set to 50, 127, 210.</para>
                <para lang="en">しきい値を 50、 127、 210 に設定</para>
              </caption>
            </mediaobject>
          </figure>
        </listitem>
      </varlistentry>
    </variablelist>
  </sect3>
</sect2>
