<?xml version="1.0" encoding="UTF-8"?>
<!DOCTYPE sect2 PUBLIC "-//OASIS//DTD DocBook XML V4.3//EN"
                       "http://www.docbook.org/xml/4.3/docbookx.dtd">
<!-- section history:
  2007-06-27 Added Spanish translation by AntI
  2007-04-30 KoSt: added 'no'
  2007-01-18 it added by alessandro falappa
  2005-12-07 replaced <simplesect> by <sect3> by lexa
  2005-09-12 de added by axel.wernicke
-->
<!--2012-03-25-->
<sect2 id="plug-in-gimpressionist" xmlns:xi="http://www.w3.org/2001/XInclude">
  <title>GIMPressionist</title>

  <indexterm lang="en">
    <primary>Filters</primary>
    <secondary>Artistic</secondary>
    <tertiary>GIMPressionist</tertiary>
  </indexterm>
  <indexterm lang="en">
    <primary>GIMPressionist</primary>
  </indexterm>
  <indexterm lang="ja">
    <primary>フィルター</primary>
    <secondary sortas="ゲイジュツテキコウカ">芸術的効果</secondary>
    <tertiary>GIMPressionist</tertiary>
  </indexterm>
  <indexterm lang="ja">
    <primary>GIMPressionist</primary>
  </indexterm>

  <sect3>
    <title lang="en">Overview</title>
    <title lang="ja">概観</title>
    <figure>
      <title lang="en">
        Example for the <quote>GIMPressionist</quote> filter
      </title>
      <title lang="ja"><quote>GIMPressionist</quote>フィルターの使用例</title>
      <mediaobject>
        <imageobject>
          <imagedata format="JPG"
            fileref="images/filters/examples/taj_orig.jpg"/>
        </imageobject>
        <caption>
          <para lang="en">Original image</para>
          <para lang="ja">元画像</para>
        </caption>
      </mediaobject>
      <mediaobject>
        <imageobject>
          <imagedata format="JPG"
            fileref="images/filters/examples/artistic-taj-gimpressionist.jpg"/>
        </imageobject>
        <caption>
          <para lang="en">Filter <quote>GIMPressionist</quote> applied</para>
          <para lang="ja"><quote>GIMPressionist</quote>フィルター適用後</para>
        </caption>
      </mediaobject>
    </figure>
    <para lang="en">
      The GIMPressionist filter is the king of Artistic filters. It can do
      what <link linkend="plug-in-cubism">Cubism</link> and
      <link linkend="plug-in-apply-canvas">Apply Canvas</link> do and much
      more. It gives your image the look of a painting. All is going as if
      your image was painted again on a paper and with a brush you'd have
      chosen. It works on the active layer or selection.
    </para>
    <para lang="ja">
      <guimenuitem>GIMPressionist...</guimenuitem> フィルターは
      芸術的効果フィルターの王者です。
      <link linkend="plug-in-cubism">キュービズム</link> フィルターや
      <link linkend="plug-in-apply-canvas">キャンバス地</link> フィルターや
      その他いろんなフィルターが行なっていることをこなせます。 画像を絵画の
      ように見せる機能があります。 あたかも絵筆を選びつつまるで紙の上に描き
      直したような処理が行なわれます。 このフィルターは活性レイヤーもしくは
      その選択範囲で作用します。
    </para>
  </sect3>

  <sect3>
    <title lang="en">Activating the filter</title>
    <title lang="ja">フィルターの呼び出し方</title>
    <para lang="en">
      You can find this filter via the image menu through
      <menuchoice>
        <guimenu>Filters</guimenu>
        <guisubmenu>Artistic</guisubmenu>
        <guimenuitem>GIMPressionist</guimenuitem>
      </menuchoice>.
    </para>
    <para lang="ja">
      画像ウィンドウのメニューより
      <menuchoice>
        <guimenu>フィルター</guimenu>
        <guisubmenu>芸術的効果</guisubmenu>
        <guimenuitem>GIMPressionist...</guimenuitem>
      </menuchoice>
    </para>
  </sect3>

  <sect3>
    <!-- Parameter Settings -->
    <title lang="en">Options</title>
    <title lang="ja">オプション</title>
    <figure>
      <title lang="en">GIMPressionist options</title>
      <title lang="ja">GIMPressionist のオプション</title>
      <mediaobject>
        <imageobject>
          <imagedata format="PNG"
            fileref="images/filters/artistic/gimpressionist.png"/>
        </imageobject>
      </mediaobject>
    </figure>
    <para lang="en">
      The dialog window consists of a small Preview area on the left, which is
      always visible, and a huge amount of GIMPressionist options organized in
      tabs.
    </para>
    <para lang="ja">
      ダイアログウィンドウの左側には常時様子がわかる小さな
      プレビュー区画があり、 右側にはタブで仕分けれた GIMPressionist の膨大な
      オプションがあります。
    </para>

    <sect4>
      <title lang="en">Preview</title>
      <title lang="ja">プレビュー</title>
      <para lang="en">
        All your setting changes will appear in the Preview without affecting
        the image until you click on <guibutton>OK</guibutton>. The
        <guibutton>Update</guibutton> button refreshes the preview window (it
        is not automatic, GIMPressionist has so much work to do!), and the
        <guibutton>Reset</guibutton> button reverts to the original image.
      </para>
      <para lang="ja">
        <guibutton>OK</guibutton> ボタンで変更を確定するまでは、 ダイアログで
        設定した内容を反映できる縮小見本画像をご利用ください。
        <guibutton>更新</guibutton> ボタンをクリックすると縮小見本画像が最新の
        状態に変わります。 (このプレビュー機能には自動更新がありません。
        GIMPressionist フィルターはとても沢山の作業をこなしているのです。)
        <guibutton>リセット</guibutton> ボタンをクリックすれば元画像の表示に
        戻ります。
      </para>
    </sect4>

    <sect4>
      <title lang="en">Preset tab</title>
      <title lang="ja">プリセットタブ</title>
      <figure>
        <title lang="en"><quote>Presets</quote> tab options</title>
        <title lang="ja"><quote>プリセット</quote>タブのオプション</title>
        <mediaobject>
          <imageobject>
            <imagedata format="PNG"
              fileref="images/filters/artistic/gimpressionist1.png"/>
          </imageobject>
        </mediaobject>
      </figure>
      <para lang="en">
        GIMPressionist has a lot of parameters. When combined, they
        give an astronomical number of possibilities. So, it is important,
        when an interesting preset has been found, to save it and also to
        send it to the plugin author if exceptional. Per contra, the
        intricacy of all these parameters makes difficult understanding
        and foreseeing how each one works.
      </para>
      <para lang="ja">
        GIMPressionist には多くのパラメーターがあります。 これらを組み合わせれば
        その可能性は天文学的な数になります。 ですから面白いプリセットを
        見付けたらそれを保存しておくのは大事なことです。 とくに凄いものが
        できたらプラグインの作者にそのプリセットを送りましょう。 しかし裏を
        返せばそんな全部のパラメーターが入り組んでいるせいで理解するのも
        それぞれのはたらきを予測するのも難しくなっています。
      </para>
      <variablelist>
        <title lang="en">Presets options</title>
        <title lang="ja">プリセットのオプション</title>
        <varlistentry>
          <term lang="en">Save Current</term>
          <term lang="ja">現状保存...</term>
          <listitem>
            <para lang="en">
              Save current parameters.
              You can give a name in the input box on the left and a short
              description in the dialog that appear.
            </para>
            <para lang="ja">
              このボタンは現在の全てのタブで設定したパラメーターをファイルに
              保存します。 名前は左隣の記入欄で、 概略説明文は
              出てくるダイアログ内で設定してください。
            </para>
          </listitem>
        </varlistentry>
        <varlistentry>
          <term lang="en">Apply</term>
          <term lang="ja">適用</term>
          <listitem>
            <para lang="en">
              Load the parameters of the selected preset in the list.
            </para>
            <para lang="ja">
              このボタンをクリックすると
              一覧表で選択したプリセットの設定内容が読み込まれます。
            </para>
          </listitem>
        </varlistentry>
        <varlistentry>
          <term lang="en">Delete</term>
          <term lang="ja">削除</term>
          <listitem>
            <para lang="en">
              Delete the selected preset. You can delete only the presets you
              have created.
            </para>
            <para lang="ja">
              このボタンをクリックすると
              一覧表で選択したプリセットが削除されます。
            </para>
          </listitem>
        </varlistentry>
        <varlistentry>
          <term lang="en">Refresh</term>
          <term lang="ja">更新</term>
          <listitem>
            <para lang="en">Update the preset list.</para>
            <para lang="ja">
              このボタンをクリックすると
              プリセットの一覧表が現在の状態に更新されます。
            </para>
          </listitem>
        </varlistentry>
      </variablelist>
    </sect4>

    <sect4>
      <title lang="en">Paper tab</title>
      <title lang="en">紙タブ</title>
      <figure>
        <title lang="en"><quote>Paper</quote> tab options</title>
        <title lang="ja"><quote>紙</quote>タブのオプション</title>
        <mediaobject>
          <imageobject>
            <imagedata format="PNG"
              fileref="images/filters/artistic/gimpressionist2.png"/>
          </imageobject>
        </mediaobject>
      </figure>
      <para lang="en">
        This tab concerns the texture of the canvas your image will be painted
        on. You have a list of textures and a <guilabel>Preview</guilabel> for
        the selected texture. A description is displayed on the right for
        every texture when selected.
      </para>
      <para lang="ja">
        このタブでは画像が描かれるキャンバスとなる紙や石版やキャンバス地などの
        素材を設定します。 素材は一覧表に並べられ選択すると右側の生地見本に
        表示されます。 またその素材の説明も右側に示されます。
      </para>
      <variablelist>
        <title lang="en">Paper options</title>
        <title lang="ja">紙のオプション</title>
        <varlistentry>
          <term lang="en">Invert</term>
          <term lang="ja">反転</term>
          <listitem>
            <para lang="en">
              Inverts the paper texture: what was a hollow turns to a bump
              and vice-versa.
            </para>
            <para lang="ja">
              素材の凹凸を反転します。 窪みは盛り上がりふくらみは穿たれます。
            </para>
          </listitem>
        </varlistentry>
        <varlistentry>
          <term lang="en">Overlay</term>
          <term lang="ja">オーバーレイ</term>
          <listitem>
            <para lang="en">
              Apply the paper as it, without embossing it. It looks like
              if a transparent paper has been overlayed on the image.
            </para>
            <para lang="ja">
              凹凸のない紙として使います。 画像に透明な紙が被されたような
              見え方をします。
            </para>
          </listitem>
        </varlistentry>
        <varlistentry>
          <term lang="en">Scale</term>
          <term lang="ja">拡大縮小</term>
          <listitem>
            <para lang="en">
              Specifies the scale of the texture (in % of the original
              file): controls the graininess of the texture.
            </para>
            <para lang="ja">
              素材の倍率を百分率で設定します。 素材の粒度の違いが現れます。
              3.0 パーセントから 150.0 パーセントまでの範囲で指定してください。
            </para>
          </listitem>
        </varlistentry>
        <varlistentry>
          <term lang="en">Relief</term>
          <term lang="ja">浮き彫り</term>
          <listitem>
            <para lang="en">
              Specifies the amount of embossing to apply (3-150).
            </para>
            <para lang="ja">
              生地の素材の起伏量を設定します。 0.0 パーセントから 
              100.0 パーセントまでの範囲で指定してください。
            </para>
          </listitem>
        </varlistentry>
      </variablelist>
    </sect4>

    <sect4>
      <title lang="en">Brush tab</title>
      <title lang="ja">ブラシタブ</title>
      <figure>
        <title lang="en"><quote>Brush</quote> tab options</title>
        <title lang="ja"><quote>ブラシ</quote>タブのオプション</title>
        <mediaobject>
          <imageobject>
            <imagedata format="PNG"
              fileref="images/filters/artistic/gimpressionist3.png"/>
          </imageobject>
        </mediaobject>
      </figure>
      <para lang="en">
        <quote>Brush</quote> is a general term for any material used to paint.
        A list of brushes is available with a <guilabel>Preview</guilabel> for
        the selected one.
      </para>
      <para lang="ja">
        <quote>ブラシ</quote>は描画に使われるどの資材にとっても通用します。
        ブラシの一覧表で選択されたブラシは右隣に見本表示がでます。
      </para>
      <variablelist>
        <title lang="en">Brush options</title>
        <title lang="ja">ブラシのオプション</title>
        <varlistentry>
          <term lang="en">Gamma</term>
          <term lang="ja">ガンマ</term>
          <listitem>
            <para lang="en">
              Changes the gamma (luminosity) of the selected brush. The
              gamma correction brightens or darkens midtones.
            </para>
            <para lang="ja">
              選択したブラシのガンマ値 (光度) を変更できます。 ガンマ補正で
              中間階調を明るくしたり暗くしたりできます。
            </para>
          </listitem>
        </varlistentry>
        <varlistentry>
          <term lang="en">Select</term>
          <term lang="ja">選択</term>
          <listitem>
            <para lang="en">
              You can also use a brush pattern you have created by
              selecting its image (arrow button on the Select line). This
              image must be on your screen before you launch the filter to
              be taken in account. Of course, don't use big images.
            </para>
            <para lang="en">
              If your image has several layers, they also will be
              displayed in the Select list and can be used as a brush.
              When selected, the layer appears in the brush preview and
              the normal brush is deselected.
            </para>
            <para lang="en">
              The <guibutton>Save as</guibutton>
              button allows you to save the selected brush.
            </para>
            <para lang="ja">
              ブラシの形質には画像から選択して作成したものも利用できます。
              (選択欄の右端の矢印をクリックすれば画像の一覧表になります。) 
              ここで表示される画像はこのフィルターを呼び出した時点で
              <acronym>GIMP</acronym>が画面上に開いているものだけです。
              当然ですが大きな画像をブラシにしないでください。
            </para>
            <para lang="ja">
              画像に複数のレイヤーがあると選択リストにはレイヤーが個々に
              表示されますのでレイヤーを選べばそれもブラシに利用できます。
            </para>
            <para lang="ja">
              <guibutton>別名で保存</guibutton> ボタンは
              選択したブラシを保存するときに使用します。
            </para>
          </listitem>
        </varlistentry>
        <varlistentry>
          <term lang="en">Aspect ratio</term>
          <term lang="ja">縦横比</term>
          <listitem>
            <para lang="en">
              Specifies the brush proportions, height (0 -1) and width (0 +1).
            </para>
            <para lang="ja">
              ブラシの形状を変えます。 0.00 が無変化、 -1.00 から 0.99 が
              水平方向に拡大するか垂直方向に縮小して横長に、 0.01 から 1.00
              までが垂直方向に拡大するか水平方向に縮小して縦長になります。
            </para>
          </listitem>
        </varlistentry>
        <varlistentry>
          <term lang="en">Relief</term>
          <term lang="ja">浮き彫り</term>
          <listitem>
            <para lang="en">
              Specifies the amount of paint used for each stroke. This may
              evoke painting with a palette knife.
            </para>
            <para lang="ja">
              ブラシの筆触一回あたりの絵の具の量を設定します。 パレットナイフを
              使った筆遣いを彷彿とさせます。
            </para>
          </listitem>
        </varlistentry>
      </variablelist>
    </sect4>

    <sect4 id="gimpressionist-orientation-options">
      <term lang="en">Orientation tab</term>
      <term lang="ja">向きタブ</term>
      <figure>
        <title lang="en"><quote>Orientation</quote> tab options</title>
        <title lang="ja"><quote>向き</quote>タブのオプション</title>
        <mediaobject>
          <imageobject>
            <imagedata format="PNG"
              fileref="images/filters/artistic/gimpressionist4.png"/>
          </imageobject>
        </mediaobject>
      </figure>
      <para lang="en">
        This tab allows to set the orientation of the brush strokes. A painter
        is not obliged to go over with the same paintbrush angle.  To perform
        some effects, he can vary their orientation.
      </para>
      <para lang="ja">
        このタブでは筆遣いの向きを設定できます。 筆をいつも同じ向きに運ばざるを
        えない画家はいません。 何らかの効果を狙ってその向きを変えることは
        よくあります。
      </para>
      <variablelist>
        <title lang="en">Orientation options</title>
        <title lang="ja">向きのオプション</title>
        <varlistentry>
          <term lang="en">Directions</term>
          <term lang="ja">方向バリエーション数</term>
          <listitem>
            <para lang="en">
              With this option, you can set how many times the brush will pass
              through a same place, with each time a different direction,
              resulting in a more and more thick paint.
            </para>
            <para lang="ja">
              このスライダーで、 同じところをブラシが向きを換え繰り返しなぞる
              回数を設定できます。 回数が多くなればなるほど塗った色が
              濃くなります。
            </para>
          </listitem>
        </varlistentry>
        <varlistentry>
          <term lang="en">Start Angle</term>
          <term lang="ja">開始角度</term>
          <listitem>
            <para lang="en">
              Specifies the general direction of the strokes, the angle that
              the angle range will start from. Directions are often chosen to
              give some movement to the image.
            </para>
            <para lang="ja">
              このスライダーで筆遣いの中心的な方向を決めます。 この方向を軸に
              <guilabel>角度範囲</guilabel> 内で向きをばらつかせ筆が進みます。
              画像に対するさまざまな動きをつけるため方向が幾度も選び出されます。
            </para>
          </listitem>
        </varlistentry>
        <varlistentry>
          <term lang="en">Angle Span</term>
          <term lang="ja">角度範囲</term>
          <listitem>
            <para lang="en">
              Specifies the angle, the sector, of the stroke <quote>fan</quote>.
            </para>
            <para lang="ja">
              筆触は開始角度を中心にこの扇型の範囲内で進む向きに変化をつけます。
            </para>
          </listitem>
        </varlistentry>
        <varlistentry>
          <term lang="en">Orientation</term>
          <term lang="ja">向き</term>
          <listitem>
            <para lang="en">Specifies the direction of the brush strokes.</para>
            <para lang="ja">筆触の方向を制御する基準をここで指定します。</para>
            <variablelist>
              <varlistentry>
                <term lang="en"><guilabel>Value</guilabel></term>
                <term lang="ja"><guilabel>明度</guilabel></term>
                <listitem>
                  <para lang="en">
                    Let the Value (luminosity) of the region determine the
                    direction of the stroke.
                  </para>
                  <para lang="ja">
                    筆触の向きの変化は付近の明度に従います。
                  </para>
                </listitem>
              </varlistentry>
              <varlistentry>
                <term lang="en"><guilabel>Radius</guilabel></term>
                <term lang="ja"><guilabel>中央からの距離</guilabel></term>
                <listitem>
                  <para lang="en">
                    The distance from the center of the image determines the
                    direction of the stroke.
                  </para>
                  <para lang="ja">
                    画像の中央からの距離で筆触の向きを決めます。
                  </para>
                </listitem>
              </varlistentry>
              <varlistentry>
                <term lang="en"><guilabel>Random</guilabel></term>
                <term lang="ja"><guilabel>ランダム</guilabel></term>
                <listitem>
                  <para lang="en">
                    Select a random direction for each stroke.
                  </para>
                  <para lang="ja">筆触の向きは不規則に変化します。</para>
                </listitem>
              </varlistentry>
              <varlistentry>
                <term lang="en"><guilabel>Radial</guilabel></term>
                <term lang="ja"><guilabel>中央からの方向</guilabel></term>
                <listitem>
                  <para lang="en">
                    Let the direction from the center determine the direction
                    of the stroke.
                  </para>
                  <para lang="ja">
                    筆触の向きは画像の中央からの向きを参考にして決まります。
                  </para>
                </listitem>
              </varlistentry>
              <varlistentry>
                <term lang="en"><guilabel>Flowing</guilabel></term>
                <term lang="ja"><guilabel>流れるように</guilabel></term>
                <listitem>
                  <para lang="en">
                    Not a direction question here: the strokes follow a
                    <quote>flowing</quote> pattern.
                  </para>
                  <para lang="ja">
                    筆触の向きは内部で生成した流れるようなパターンの
                    方向マップに従って進みます。
                  </para>
                </listitem>
              </varlistentry>
              <varlistentry>
                <term lang="en"><guilabel>Hue</guilabel></term>
                <term lang="ja"><guilabel>色相</guilabel></term>
                <listitem>
                  <para lang="en">
                    Let the hue of the region determine the direction of the
                    stroke.
                  </para>
                  <para lang="ja">筆触の向きは付近の色相で決まります。</para>
                </listitem>
              </varlistentry>
              <varlistentry>
                <term lang="en"><guilabel>Adaptive</guilabel></term>
                <term lang="ja"><guilabel>適応的</guilabel></term>
                <listitem>
                  <para lang="en">
                    The brush direction that matches the original image the
                    closest is selected.
                  </para>
                  <para lang="ja">元の画像に最適な向きに筆が進みます。</para>
                </listitem>
              </varlistentry>
              <varlistentry>
                <term lang="en"><guilabel>Manual</guilabel></term>
                <term lang="ja"><guilabel>手動設定</guilabel></term>
                <listitem>
                  <para lang="en">
                    The <guilabel>Edit</guilabel> button opens the
                    <link linkend="gimpressionist-orient-map-editor">Edit
                    orientation Map dialog</link> that allows you to set the
                    directions manually.
                  </para>
                  <para lang="ja">
                    <guibutton>編集</guibutton> ボタンをクリックすると
                    <link linkend="gimpressionist-orient-map-editor">
                    方向マップエディターダイアログ</link> が開かれ、 運筆方向を
                    描けます。
                  </para>
                </listitem>
              </varlistentry>
            </variablelist> <!--end of "brush stroke Orientation"-->
          </listitem>
        </varlistentry>
      </variablelist> <!--end of "Orientation options"-->
    </sect4>

    <sect4 id="gimpressionist-size-options">
      <title lang="en">Size tab</title>
      <title lang="ja">サイズタブ</title>
      <figure>
        <title lang="en"><quote>Size</quote> tab options</title>
        <title lang="ja"><quote>サイズ</quote>タブのオプション</title>
        <mediaobject>
          <imageobject>
            <imagedata format="PNG"
              fileref="images/filters/artistic/gimpressionist5.png"/>
          </imageobject>
        </mediaobject>
      </figure>
      <para lang="en">
        This tab allows you to set the number of brush sizes that will be used
        to paint, the limits of variation of these sizes and the criterion
        used to determine them.
      </para>
      <para lang="ja">
        このタブでは描画に使われるブラシの大きさについて、 その可変段数と、
        変化の度合いの制限と、 大きさを変える基準となる指標を設定できます。
      </para>
      <variablelist>
        <title lang="en">Size options</title>
        <title lang="ja">サイズのオプション</title>
        <para lang="en">
          You can specify how many brush sizes are to be used and their sizes.
        </para>
        <para lang="ja">
          大きさの異なるブラシを何種類使うかということとその大きさについて
          設定できます。
        </para>
        <varlistentry>
          <term lang="en">Sizes</term>
          <term lang="ja">サイズバリエーション数</term>
          <listitem>
            <para lang="en">The number of brush sizes to use.</para>
            <para lang="ja">
              ブラシの大きさを何段階まで切り替えて使えるようにするかをここで
              指定します。
            </para>
          </listitem>
        </varlistentry>
        <varlistentry>
          <term lang="en">Minimum size</term>
          <term lang="en">Maximum size </term>
          <term lang="ja">最小サイズ</term>
          <term lang="ja">最大サイズ</term>
          <listitem>
            <para lang="en">
              The brush sizes are between these two values. The greater the
              size, greater the length and width of strokes.
            </para>
            <para lang="ja">
              ブラシの大きさはこの両限度の間を変動します。 大きくすれば
              筆の進みも長く幅広くなります。
            </para>
          </listitem>
        </varlistentry>
        <varlistentry>
          <term lang="en">Sizes</term>
          <term lang="ja">サイズの決定基準</term>
          <listitem>
            <para lang="en">
              You have there options to specify how the size of strokes
              will be determined.
            </para>
            <para lang="ja">
              ブラシの大きさを決めるオプションをつぎのいずれかに
              選んでください。
            </para>
            <variablelist>
              <varlistentry>
                <term lang="en"><guilabel>Value</guilabel></term>
                <term lang="ja"><guilabel>明度</guilabel></term>
                <listitem>
                  <para lang="en">
                    Let the Value (luminosity) of the region determine the
                    size of the stroke.
                  </para>
                  <para lang="ja">
                    筆触の大きさの変化は付近の明度に従います。
                  </para>
                </listitem>
              </varlistentry>
              <varlistentry>
                <term lang="en"><guilabel>Radius</guilabel></term>
                <term lang="ja"><guilabel>中央からの距離</guilabel></term>
                <listitem>
                  <para lang="en">
                    The distance from the center of the image determines the
                    size of the stroke.
                  </para>
                  <para lang="ja">
                    画像の中央からの距離で筆触の大きさを決めます。
                  </para>
                </listitem>
              </varlistentry>
              <varlistentry>
                <term lang="en"><guilabel>Random</guilabel></term>
                <term lang="ja"><guilabel>ランダム</guilabel></term>
                <listitem>
                  <para lang="en">Select a random size for each stroke.</para>
                  <para lang="ja">筆触の大きさは不規則に変化します。</para>
                </listitem>
              </varlistentry>
              <varlistentry>
                <term lang="en"><guilabel>Radial</guilabel></term>
                <term lang="ja"><guilabel>中央からの方向</guilabel></term>
                <listitem>
                  <para lang="en">
                    Let the direction from the center determine the size of
                    the stroke.
                  </para>
                  <para lang="ja">
                    筆触の大きさは画像の中央からの向きで決まります。
                  </para>
                </listitem>
              </varlistentry>
              <varlistentry>
                <term lang="en"><guilabel>Flowing</guilabel></term>
                <term lang="ja"><guilabel>流れるように</guilabel></term>
                <listitem>
                  <para lang="en">
                    Not a length question here: the strokes follow a
                    <quote>flowing</quote> pattern.
                  </para>
                  <para lang="ja">
                    筆触の大きさは内部で生成した流れるようなパターンの
                    サイズマップに従って変わります。
                  </para>
                </listitem>
              </varlistentry>
              <varlistentry>
                <term lang="en"><guilabel>Hue</guilabel></term>
                <term lang="ja"><guilabel>色相</guilabel></term>
                <listitem>
                  <para lang="en">
                    Let the hue of the region determine the size of the
                    stroke.
                  </para>
                  <para lang="ja">筆触の大きさは付近の色相で決まります。</para>
                </listitem>
              </varlistentry>
              <varlistentry>
                <term lang="en"><guilabel>Adaptive</guilabel></term>
                <term lang="ja"><guilabel>適応的</guilabel></term>
                <listitem>
                  <para lang="en">
                    The brush size that matches the original image the closest
                    is selected.
                  </para>
                  <para lang="ja">
                    元の画像に最適な大きさのブラシを使います。
                  </para>
                </listitem>
              </varlistentry>
              <varlistentry>
                <term lang="en"><guilabel>Manual</guilabel></term>
                <term lang="ja"><guilabel>手動設定</guilabel></term>
                <listitem>
                  <para lang="en">
                    The <guilabel>Edit</guilabel> button opens the
                    <link linkend="gimpressionist-size-map-editor">Size Map
                    Editor</link>. That allows you to specify the size of
                    strokes by yourself.
                  </para>
                  <para lang="ja">
                    <guibutton>編集</guibutton> ボタンをクリックすると
                    <link linkend="gimpressionist-size-map-editor">
                    サイズマップエディターダイアログ</link> が開かれます。 
                    筆触の大きさを制御できます。
                  </para>
                </listitem>
              </varlistentry>
            </variablelist> <!--end of "brush stroke Size"-->
          </listitem>
        </varlistentry>
      </variablelist> <!--end of "Size options"-->
    </sect4>

    <sect4>
      <title lang="en">Placement tab</title>
      <title lang="ja">配置タブ</title>
      <figure>
        <title lang="en"><quote>Placement</quote> tab options</title>
        <title lang="ja"><quote>配置</quote>タブのオプション</title>
        <mediaobject>
          <imageobject>
            <imagedata format="PNG"
              fileref="images/filters/artistic/gimpressionist6.png"/>
          </imageobject>
        </mediaobject>
      </figure>
      <para lang="en">
        In this tab you can set how strokes will be distributed.
      </para>
      <para lang="ja">
        このタブでは筆を走らせる配分に変化をもたらす調整ができます。
      </para>
      <variablelist>
        <title lang="en">Placement options</title>
        <title lang="ja">配置のオプション</title>
        <varlistentry>
          <term lang="en">Placement</term>
          <term lang="ja">配置</term>
          <listitem>
            <para lang="en">
              In the preview of the Orientation Map Editor, all small
              arrows look like a flow around objects. Inside this flow,
              strokes may be placed in two different ways:
            </para>
            <para lang="ja">
              方向マップエディターではプレビュー画面を埋め尽くす小さな矢印の
              すべてが描かれている物体の周囲の流れを描くように見えています。
              この流れにのって走る筆の配置はつぎの異なる 2 つのいずれかの
              方法に従います。
            </para>
            <variablelist>
              <varlistentry>
                <term lang="en"><guilabel>Randomly</guilabel></term>
                <term lang="ja"><guilabel>ランダムに</guilabel></term>
                <listitem>
                  <para lang="en">
                    Places strokes randomly. This produces a more realistic
                    paint.
                  </para>
                  <para lang="ja">
                    不規則に筆が重ねられます。 より本物らしく見せる方法です。
                  </para>
                </listitem>
              </varlistentry>
              <varlistentry>
                <term lang="en"><guilabel>Evenly distributed</guilabel></term>
                <term lang="ja"><guilabel>均等に</guilabel></term>
                <listitem>
                  <para lang="en">
                    Strokes are evenly distributed across the image.
                  </para>
                  <para lang="ja">
                    画像全体を通して均等な筆の重ねかたをします。
                  </para>
                </listitem>
              </varlistentry>
            </variablelist>
          </listitem>
        </varlistentry>
        <varlistentry>
          <term lang="en">Stroke Density</term>
          <term lang="ja">ストローク密度</term>
          <listitem>
            <para lang="en">
              The greater the density the closer the strokes. With a low
              density, the paper or background may be visible in unstroke
              areas.
            </para>
            <para lang="ja">
              密度を上げると筆はさらに密接に重なります。 密度を下げると筆の
              入らない隙間ができ紙面か背景が見えてくるようになります。
            </para>
          </listitem>
        </varlistentry>
        <varlistentry>
          <term lang="en">Centered</term>
          <term lang="ja">中心に集中させる</term>
          <listitem>
            <para lang="en">Focus brush strokes around center.</para>
            <para lang="ja">
              画像の中心とその周囲に比較的多くの筆が入ります。
            </para>
          </listitem>
        </varlistentry>
      </variablelist>
    </sect4>

    <sect4>
      <title lang="en">Color tab</title>
      <title lang="ja">色タブ</title>
      <figure>
        <title lang="en"><quote>Color</quote> tab options</title>
        <title lang="ja"><quote>色</quote>タブのオプション</title>
        <mediaobject>
          <imageobject>
            <imagedata format="PNG"
              fileref="images/filters/artistic/gimpressionist7.png"/>
          </imageobject>
        </mediaobject>
      </figure>
      <para lang="en">
        In this tab, you can set what the stroke color will be.
      </para>
      <para lang="ja">
        このタブでは絵筆にどんな色が使われるかを設定します。
      </para>
      <variablelist>
        <title lang="en">Color options</title>
        <title lang="ja">色のオプション</title>
        <varlistentry>
          <term lang="en">Color</term>
          <term lang="ja">カラー</term>
          <listitem>
            <para lang="en">You can set the stroke color in two ways:</para>
            <para lang="ja">
              筆にのる色の選ばれ方にはつぎの2種類があります。
            </para>
            <variablelist>
              <varlistentry>
                <term lang="en"><guilabel>Average under brush</guilabel></term>
                <term lang="ja"><guilabel>ブラシ下の平均</guilabel></term>
                <listitem>
                  <para lang="en">
                    Stroke color is computed from the average of all
                    pixels under the brush.
                  </para>
                  <para lang="ja">
                    ブラシの大きさの範囲にある全ての画素の平均的な色が
                    使われます。
                  </para>
                </listitem>
              </varlistentry>
              <varlistentry>
                <term lang="en"><guilabel>Center of brush</guilabel></term>
                <term lang="ja"><guilabel>ブラシの中心</guilabel></term>
                <listitem>
                  <para lang="en">
                    Samples the color from the pixel in the center of the
                    brush.
                  </para>
                  <para lang="ja">
                    ブラシの中心の直下にある画素の色が使われます。
                  </para>
                </listitem>
              </varlistentry>
            </variablelist>
          </listitem>
        </varlistentry>
        <varlistentry>
          <term lang="en">Color noise</term>
          <!--ノイズを付加-->
          <term lang="ja">色ノイズ</term>
          <listitem>
            <para lang="en">
              This slider, and its input box, allow you to introduce noise
              in the stroke color, that will look less homogeneous.
            </para>
            <para lang="ja">
              このスライダーや数値記入欄に設定した数値が高いほど、 ひと筆に
              のる色にノイズが入るようになり、 単調な印象が減ります。
            </para>
          </listitem>
        </varlistentry>
      </variablelist>
    </sect4>

    <sect4>
      <term lang="en">General tab</term>
      <term lang="ja">全般タブ</term>
      <figure>
        <title lang="en"><quote>General</quote> tab options</title>
        <title lang="ja"><quote>全般</quote>タブのオプション</title>
        <mediaobject>
          <imageobject>
            <imagedata format="PNG"
              fileref="images/filters/artistic/gimpressionist8.png"/>
          </imageobject>
        </mediaobject>
      </figure>
      <para lang="en">
        In this tab you can set what will be the background and the relief
        of brush strokes.
      </para>
      <para lang="ja">
        このタブでは背景の表現と、 筆跡の起伏のつけかたについて設定できます。
      </para>
      <variablelist>
        <title lang="en">General option</title>
        <title lang="ja">全般のオプション</title>
        <varlistentry>
          <term lang="en">Background</term>
          <term lang="ja">背景</term>
          <listitem>
            <variablelist>
              <varlistentry>
                <term lang="en"><guilabel>Keep Original</guilabel></term>
                <!--元画像を残す-->
                <term lang="ja"><guilabel>オリジナルを残す</guilabel></term>
                <listitem>
                  <para lang="en">
                    The original image will be used as a background.
                  </para>
                  <para lang="ja">元画像を背景に使います。</para>
                </listitem>
              </varlistentry>
              <varlistentry>
                <term lang="en"><guilabel>From Paper</guilabel></term>
                <term lang="ja"><guilabel>紙から</guilabel></term>
                <listitem>
                  <para lang="en">
                    Copy the texture of the selected paper as a background.
                  </para>
                  <para lang="ja">
                    <quote>紙</quote>タブで選択した生地の素材感が現れます。
                  </para>
                </listitem>
              </varlistentry>
              <varlistentry>
                <term lang="en"><guilabel>Solid</guilabel></term>
                <!--単色-->
                <term lang="ja"><guilabel>ソリッド</guilabel></term>
                <listitem>
                  <para lang="en">
                    By clicking on the color dwell you can select a solid
                    colored background.
                  </para>
                  <para lang="ja">
                    単色の背景です。 色だまりボタンをクリックすると
                    色が選べる色変更ダイアログが現れます。
                  </para>
                </listitem>
              </varlistentry>
              <varlistentry>
                <term lang="en"><guilabel>Transparent</guilabel></term>
                <term lang="ja"><guilabel>透明</guilabel></term>
                <listitem>
                  <para lang="en">
                    Use a transparent background. Only the painted strokes
                    will be visible. This option is available only if your
                    image has an Alpha channel.
                  </para>
                  <para lang="ja">
                    透明な背景です。 ブラシで塗色されたところだけ見えるように
                    なります。 このオプションは画像にアルファチャンネルが
                    ある場合のみ利用できます。
                  </para>
                </listitem>
              </varlistentry>
            </variablelist>
          </listitem>
        </varlistentry>
        <varlistentry>
          <term lang="en">Paint Edges</term>
          <term lang="ja">端も塗る</term>
          <listitem>
            <para lang="en">
              If it is disabled, a thin border will not be painted around
              the outside border of the image.
            </para>
            <para lang="ja">
              このオプションを無効にすると、 画像からはみ出した物体の細い
              縁取り線は画像の縁では描かれません。
            </para>
          </listitem>
        </varlistentry>
        <varlistentry>
          <term lang="en">Tileable</term>
          <term lang="ja">タイル化可能</term>
          <listitem>
            <para lang="en">
              If checked, the resulting image will be seamlessly tileable.
              The right side will match the left side and the top will
              match the bottom. This is interesting if your image will be
              repeatedly used in a Web background.
            </para>
            <para lang="ja">
              このオプションを有効にすると、 並べると継ぎ目の目立たないタイル化
              可能な画像になります。 右辺は左辺に、 上辺は下辺に、 ぴったり
              絵柄が繋がるように筆が運ばれます。 このような画像はウェブページで
              背景画像に使うと連続して並べても違和感がないので好都合です。
            </para>
          </listitem>
        </varlistentry>
        <varlistentry>
          <term lang="en">Drop Shadow</term>
          <term lang="ja">ドロップシャドウ</term>
          <listitem>
            <para lang="en">Add a shadow effect to each brush stroke.</para>
            <para lang="ja">ひと筆ひと筆に影をつけます。</para>
          </listitem>
        </varlistentry>
        <varlistentry>
          <term lang="en">Edge Darken</term>
          <term lang="ja">端の暗度</term>
          <listitem>
            <para lang="en">
              How much to darken the edges of each brush stroke. This
              increases paint relief or thickness.
            </para>
            <para lang="ja">
              このスライダーで筆触の縁をどの程度暗くするかを調節します。 
              値を大きくすると絵の具の盛り上がりか太さが強調されます。
            </para>
          </listitem>
        </varlistentry>
        <varlistentry>
          <term lang="en">Shadow Darken</term>
          <term lang="ja">ドロップシャドウの暗度</term>
          <listitem>
            <para lang="en">How much to darken the brush shadow.</para>
            <para lang="ja">
              このスライダーでブラシの影をどの程度暗くするかを調節します。
            </para>
          </listitem>
        </varlistentry>
        <varlistentry>
          <term lang="en">Shadow Depth</term>
          <term lang="ja">ドロップシャドウの深度</term>
          <listitem>
            <para lang="en">
              How far apart from the object the drop shadow should be.
            </para>
            <para lang="ja">
              このスライダーで落ちた影と物体がどの程度離れるかを調節します。
            </para>
          </listitem>
        </varlistentry>
        <varlistentry>
          <term lang="en">Shadow Blur</term>
          <term lang="ja">ドロップシャドウのぼかし量</term>
          <listitem>
            <para lang="en">How much to blur the drop shadow.</para>
            <para lang="ja">
              このスライダーで落ちる影につけるぼかしの程度を調節します。
            </para>
          </listitem>
        </varlistentry>
        <varlistentry>
          <term lang="en">Deviation Threshold</term>
          <term lang="ja">しきい値</term>
          <listitem>
            <para lang="en">
              A bail-out value for adaptive selections of brush size.
            </para>
            <para lang="ja">
              このスライダーでブラシの大きさにぴったりの選択範囲でなくても
              よくなるしきい値を設定します。
            </para>
          </listitem>
        </varlistentry>
      </variablelist>
    </sect4>
  </sect3>

  <!-- GIMPressionist Orientation Map Editor
       (id=gimpressionist-orientation-map-editor) -->
  <xi:include href="GIMPressionist-orientmap.xml"/>

  <!-- GIMPressionist Size Map Editor (id=gimpressionist-size-map-editor) -->
  <xi:include href="GIMPressionist-sizemap.xml"/>

</sect2>
