<?xml version="1.0" encoding="UTF-8"?>
<!DOCTYPE sect1 PUBLIC "-//OASIS//DTD DocBook XML V4.3//EN"
                       "http://www.docbook.org/xml/4.3/docbookx.dtd">
<!--  section history:
  2008-03-23 Added Korean translation by Mr.Dust
  2007-06-22 Added Spanish translation by AntI
  2007-06-06 alex falappa: added 'it' translation
  2007-05-28 KoSt: added 'no'
  2007-05-11 lexa: initial version
-->
<!--2009-07-16-->
<sect1 id="gimp-tutorial-quickies">
  <title lang="en">GIMPLite Quickies</title>
  <title lang="ja">GIMP早分かり</title>
  <indexterm lang="en">
    <primary>Tutorial</primary>
  </indexterm>
  <indexterm lang="ja">
    <primary sortas="エンシュウ">演習</primary>
  </indexterm>

  <para lang="en">
    This tutorial is based on text and images Copyright © 2004 Carol Spears.
    The original tutorial can be found in the Internet
    <xref linkend="bibliography-online-tutorial02"/>.
  </para>
  <para lang="ja">
    この演習は Carol Spears 氏の著作(著作権 &#xa9; 2004) Tutorial: GIMPLite
    Quickies の文と画像がもとになっています。 原本はインターネット上で
    <xref linkend="bibliography-online-tutorial02" />
    入手できます。
  </para>

  <sect2>
    <title lang="en">Intention</title>
    <title lang="ja">この演習の意図</title>
    <para lang="en">
      So, <acronym>GIMP</acronym> is installed on your computer, you need to
      make a quick
      change to an image for some project, but don't want to learn about
      computer graphics just to change an imaçe; totally understandable.
      <acronym>GIMP</acronym> is a powerful image manipulator with many
      options and tools. However, it is quick and somewhat intuitive (after a
      time) for the small jobs as well. Hopefully, these quickies will help
      you with your quick problem and help you to stay friends with The
      <acronym>GIMP</acronym>;
      and ready for the more complex tools and methods later, when you have
      the time and inspiration.
    </para>
    <para lang="en">
      A couple of words about the images used here. The images came from APOD
      <xref linkend="bibliography-online-apod01"/>,
      Astronomy Picture of the Day. The screenshots were taken on my desktop
      which is sporting this APOD
      <xref linkend="bibliography-online-apod02"/> image.
    </para>
    <para lang="en">
      All you need to know to start this tutorial, is how to find and open
      your image. (
      <menuchoice>
        <guimenu>File</guimenu>
        <guimenuitem>Open</guimenuitem>
      </menuchoice> from the toolbox menu).
    </para>
    <para lang="ja">
      さてあなたはすでに<acronym>GIMP</acronym>をコンピュータにインストール
      されていて、 何かの用事で画像を加工する必要に迫られているのに、 その
      ちょっとした画像の加工のためだけにコンピュータグラフィックを勉強するのは
      御免被りたいと思っているのではないでしょうか。 その気持ち、 よく
      わかります。 <acronym>GIMP</acronym>はたくさんの装備や画材が使える強力な
      画像加工ソフトです。 でも、 小さな仕事も素早く (あともう少し経てば) 
      直観的にできるんです。 うまくいけば、 ここの簡単な演習でちょっとした
      問題は解けるようになりますし、 <acronym>GIMP</acronym>とずっと仲良く
      やってゆけるようになれます。 そして時間とアイデアがあるかぎり、 
      つぎつぎと複雑なツールや操作法が身に付くようになります。
    </para>
    <para lang="ja">
      本文で使われている画像について: 画像は日々の天文写真 (<acronym>APOD
      </acronym> (<foreignphrase>Astronomy Picture of the Day</foreignphrase>)
      <xref linkend="bibliography-online-apod01"/> からいただきました。 
      スクリーンショットは 
      <xref linkend="bibliography-online-apod02"/> 
      の画像を使用している私の画面で撮りました。
    </para>
    <para lang="ja">
      この演習を始める前に、 画像ファイルを選びだしそれを開く方法については
      ご自身で習得しておいてください。 (画像ウィンドウのメニューで
      <menuchoice>
        <guimenu>ファイル(<accel>F</accel>)</guimenu>
        <guimenuitem>開く(<accel>O</accel>)...</guimenuitem>
      </menuchoice>
      と辿ります。)
    </para>
  </sect2>
  <sect2 id="gimp-tutorial-quickie-scale">
    <title lang="en">Change the Size of an Image (Scale)</title>
    <title lang="ja">画像のサイズを変える (拡大・縮小)</title>
    <indexterm lang="en">
      <primary>Tutorial</primary>
    </indexterm>
    <indexterm lang="en">
      <primary>Image</primary>
      <secondary>scale</secondary>
    </indexterm>
    <indexterm lang="ja">
      <primary sortas="エンシュウ">演習</primary>
    </indexterm>
    <indexterm lang="ja">
      <primary sortas="ガゾウ">画像</primary>
      <secondary sortas="カクダイシュクショウ">拡大・縮小</secondary>
    <para lang="en">
      Problem: you have a huge image and you want to resize this so
      that it will display nicely on a web page. The example image is this
      beauty m51_hallas_big.jpg from APOD
      <xref linkend="bibliography-online-apod03"/>.
    </para>
    <para lang="ja">
      問題: あなたは大きな画像を持っていて、 これをウェブページに載せるのに
      最適な大きさにしたいと考えているとします。 
      この例題には<acronym>APOD</acronym>から
      <xref linkend="bibliography-online-apod03" />
      の美しい画像 <filename>m51_hallas_big.jpg</filename> を使用します。
    </para>
    <figure>
      <title lang="en">Example Image for Scaling</title>
      <title lang="ja">縮尺をかけられる例題画像</title>
      <mediaobject>
        <imageobject>
          <imagedata format="JPG"
            fileref="images/tutorials/quickie-scale-example.jpg"/>
        </imageobject>
      </mediaobject>
    </figure>
    <para lang="en">
      The first thing that you might notice is that
      <acronym>GIMP</acronym> opens the image at a logical size for
      viewing. If your image is really big like the sample image,
      <acronym>GIMP</acronym> will set the zoom so that
      it will display nicely on the screen. The zoom level is shown in the
      status area at the bottom of the Image widnow.
    </para>
    <para lang="en">
      The other thing to look at in the title-bar is the mode.
      If the mode shows as RGB in the title bar, you are fine.
      If the mode says Indexed or grayscale,
      read the <xref linkend="gimp-tutorial-quickie-change-mode"/>.
    </para>
    <para lang="ja">
      <acronym>GIMP</acronym>は画像を表示する際、 論理的な大きさで開くという
      ことをまず覚えておいてください。 例題画像のようなまさに大きな画像を開くと
      画面にうまく合うよう表示倍率を変えて表示されます。 表示倍率は画像
      ウィンドウのステータスバーの左側に表示されます。
    </para>
    <para lang="ja">
      タイトルバーに表示されるものには他に色空間のモードがあります。 ここが
      <acronym>RGB</acronym>になっていればOKです。 <quote>インデックス</quote>
      もしくは <quote>グレースケール</quote> となっている場合は、 
      <xref linkend="gimp-tutorial-quickie-change-mode"/> 
      をお読みください。
    </para>
    <figure>
      <title lang="en">GIMP Used for Image Scaling</title>
      <title lang="ja">GIMPで画像の拡大・縮小をしているようす</title>
      <mediaobject>
        <imageobject>
          <imagedata format="PNG"
            fileref="images/tutorials/quickie-scale-menu.png"/>
        </imageobject>
      </mediaobject>
    </figure>
    <para lang="en">
      Use
      <menuchoice>
        <guimenu>Image</guimenu>
        <guimenuitem>Scale Image</guimenuitem>
      </menuchoice>
      to open the Scale Image dialog. You can right click on the image to open
      the memnu, or use the menu along the top of the Image window.
      Notice that the Scale Image menu item contains three dots,
      which is a hint that a dialog will be opened.
    </para>
    <para lang="ja">
      <quote>画像の拡大・縮小</quote>ダイアログは画像ウィンドウのメニューより
      <menuchoice>
        <guimenu>画像(<accel>I</accel>)</guimenu>
        <guimenuitem>画像の拡大・縮小(<accel>S</accel>)...</guimenuitem>
      </menuchoice>
      と進むと呼び出せます。 このメニューは画像ウィンドウを <mousebutton>
      第2ボタン</mousebutton> でクリックすると呼び出せるほか、 ウィンドウ上部の
      メニューバーも使えます。 メニュー内の項目のうちその名前が
      <quote>...</quote>で終わっているものをクリックすると、 
      ダイアログが現れるようになっています。
    </para>
    <figure>
      <title lang="en">Dialog for Image Scaling in Pixels</title>
      <title lang="ja">画像をピクセル単位で縮尺しているときのダイアログ</title>
      <mediaobject>
        <imageobject>
          <imagedata format="PNG"
            fileref="images/tutorials/quickie-scale-dialog.png"/>
        </imageobject>
      </mediaobject>
    </figure>
    <para lang="en">
      If you have a desired width, put it in the dialog at the top where it
      says <guilabel>Width</guilabel>. If you don't have such a number in
      mind, you can steal the width of <acronym>GIMP</acronym>'s default image
      size, which is 256 pixels. This is shown in the figure above.
    </para>
    <para lang="ja">
      幅から決めたいときは、 <guilabel>画像サイズ (キャンバスサイズ)</guilabel>
      のところの <guilabel>幅(<accel>W</accel>)</guilabel>
      にその値を入力します。 大きさを決めかねているのでしたら、
      とりあえず<acronym>GIMP</acronym>の想提値256ピクセルに倣いましょう。
      上の図はこの作業の様子を描いています。
    </para>
    <figure>
      <title lang="en">Dialog for Image Scaling in Inches</title>
      <title lang="ja">画像をインチ単位で縮小しているときのダイアログ</title>
      <mediaobject>
        <imageobject>
          <imagedata format="PNG"
            fileref="images/tutorials/quickie-scale-dialog2.png"/>
        </imageobject>
      </mediaobject>
    </figure>
    <para lang="en">
      Perhaps you want your image to look more like a 4x6 inch photo on most
      image rendering web browsers. Switch the units to
      <quote>inches</quote> and enter 4 inches in the height box (opting for
      smaller than 4x6 rather than bigger). You can see this dialog above.
    </para>
    <para lang="en">
      Let <acronym>GIMP<.acronym> choose the other dimension length for you.
      Meaning, it requires
      more image knowledge to change both width and height and have it
      look correct. So change only one and let <acronym>GIMP</acronym>
      change the rest. To change
      the other dimension, see <xref linkend="gimp-tutorial-quickie-crop"/>.
    </para>
    <para lang="ja">
      もしもたとえば画像を一般的なウェブブラウザ上で4&times;6インチの写真
      のように表示させたいのであれば、 単位に<quote>インチ</quote>を選び、
      <guilabel>高さ(<accel>H</accel>)</guilabel> のところに4インチを
      入力しましょう。 (4&times;6インチより小さくなることはあっても
      大きくなることはありません。) 上図はその様子を再現しています。
    </para>
    <para lang="ja">
      <acronym>GIMP</acronym>でいろいろな大きさを試してみましょう。 そのうちに
      縦と横の値を変える操作や、 適度な大きさ等の画像を扱うコツがつかめて
      きます。 縦横の一方を決めて<acronym>GIMP</acronym>にもう一方を計算
      させるのもやってみましょう。 もっと他の長さに変えたいのならば
      <xref linkend="gimp-tutorial-quickie-crop" /> をご覧ください。
    </para>
  </sect2>

  <sect2 id="gimp-tutorial-quickie-jpeg">
    <title lang="en">Make JPEGs Smaller</title>
    <title lang="ja"><acronym>JPEG</acronym>を軽くする</title>
    <indexterm lang="en">
      <primary>Tutorial</primary>
    </indexterm>
    <indexterm lang="en">
      <primary>Image</primary>
      <secondary>save</secondary>
    </indexterm>
    <indexterm lang="ja">
      <primary sortas="エンシュウ">演習</primary>
    </indexterm>
    <indexterm lang="ja">
      <primary sortas="ガゾウ">画像</primary>
      <secondary sortas="ホゾン">保存</secondary>
    </indexterm>
    <figure>
      <title lang="en">Example Image for JPEG Saving</title>
      <title lang="ja"><acronym>JPEG</acronym>で保存するための例題画像</title>
      <mediaobject>
        <imageobject>
          <imagedata format="JPG"
            fileref="images/tutorials/quickie-jpeg-example.jpg"/>
        </imageobject>
      </mediaobject>
    </figure>
    <para lang="en">
      You can make your jpegs smaller (use less space on disk) without
      changing the image dimensions. The image for this example is also
      take from APOD <xref linkend="bibliography-online-apod04"/>.
      The original image is huge (3000 pixels wide) so I first I reduced
      the width and height for better use on the web (see
      <xref linkend="gimp-tutorial-quickie-scale"/>.
      Use
      <menuchoice>
        <guimenu>File</guimenu>
        <guimenuitem>Save As...</guimenuitem>
      </menuchoice>
      to open the Save Image dialog.
    </para>
    <para lang="ja">
      <acronym>JPEG</acronym>画像は大きさ (高さ・幅) はそのままにサイズを小さく
      (使うディスク容量を小さく) することができます。 この例題にも
      <acronym>APOD</acronym>
      <xref linkend="bibliography-online-apod04"/> の画像を利用しましょう。
      もとの画像はものすごく大きかった (幅3000ピクセル) ので、 ウェブページ用の
      見やすい画像にするために幅と高さを減らしました (その方法は 
      <xref linkend="gimp-tutorial-quickie-scale" /> をご覧ください)。
      画像ウィンドウのメニューより
      <menuchoice>
        <guimenu>ファイル(<accel>F</accel>)</guimenu>
        <guimenuitem>名前を付けて保存(<accel>A</accel>)...</guimenuitem>
      </menuchoice>
      と進んでください。 保存ダイアログが現れます。
    </para>
    <figure>
      <title lang="en">Save Image Dialog</title>
      <title lang="ja">画像を保存するダイアログ</title>
      <mediaobject>
        <imageobject>
          <imagedata format="PNG"
          fileref="images/tutorials/quickie-save-image-dialog-file-type.png"/>
        </imageobject>
      </mediaobject>
    </figure>
    <para lang="en">
      I generally type the full filename with extension into Name text box,
      and <acronym>GIMP</acronym> determines the file type from the
      file extension; for example, .jpg. Use the file extension list,
      circled in the figure above, to see the types supported by
      <acronym>GIMP</acronym>. The supported extensions change depending
      on your installed libraries.
      If <acronym>GIMP</acronym> complains, or if
      <quote>JPEG</quote> is grayed out in the Extensions menu,
      cancel out of everything and step through the
      <xref linkend="gimp-tutorial-quickie-change-mode"/>.
    </para>
    <para lang="en">
      The Save as JPEG dialog uses default values that reduce size while
      retaining good visual quality; this is the safest and quickest
      thing to do.
    </para>
    <para lang="ja">
      私は普段ファイル名を拡張子つきの完全型で文字入力欄に打ち込んでいます。
      <acronym>GIMP</acronym>はそのファイル拡張子 (例えば <filename
      class="extension">.jpg</filename>) を見て保存される画像のファイル形式を
      判断します。利用可能な画像ファイル形式は上図で囲んで強調した拡張子
      差し込みメニューでわかるようになっています。 サポートされているファイル
      形式と拡張子はインストールされているライブラリによって異なります。
      ここで<acronym>GIMP</acronym>が何らかの反論をしたり、 <quote>JPEG</quote>
      が拡張子メニューで灰色無効にされている場合は、 このダイアログを中止して
      <xref linkend="gimp-tutorial-quickie-change-mode"/> に従ってください。
    </para>
    <para lang="ja">
      <quote><acronym>JPEG</acronym>形式で保存</quote>ダイアログは画像の見た目
      の美しさを損なわずに容量を減らすのにちょうど良い値を既定値としています。
      そのまま進むのが最も安全で最も速い方法です。
    </para>
    <figure>
      <title lang="en">Save as JPEG dialog with poor quality.</title>
      <title lang="ja">
        <quote><acronym>JPEG</acronym>形式で保存する</quote>ダイアログ (低品質)
      </title>
      <mediaobject>
        <imageobject>
          <imagedata format="PNG"
            fileref="images/tutorials/quickie-jpeg-dialog.png"/>
        </imageobject>
      </mediaobject>
    </figure>
    <para lang="en">
      Reduce the image Quality to make the image even smaller.
      Reduced quality degrades the image, so be certain to check
      <quote>Show preview in image window</quote>. As shown in the figure
      above, a Quality of 6 produces a very poor quality image that uses very
      little disk space.
      The figure below shows a more reasonable image. A quality of 42
      produces a reasonable image using much less disk space, which will,
      in turn, load much faster on a web page. Although the image is degraded,
      it is acceptable for the intended purpose.
    </para>
    <para lang="ja">
      さらにもっと画像を軽くするには、 <guilabel>品質(<accel>Q</accel>)
      </guilabel> スライダを低い値に下げてください。
      ただし品質の低下はすなわち画質の悪化につながりますので、 
      <guilabel>画像ウィンドウでプレビュー(<accel>W</accel>)</guilabel> を有効
      にしてよく注視しましょう。 上図のように品質を6にしてみると非常に画質は
      落ちますがディスク使用量は非常に小さくなります。 下図はちょうど良い具合の
      画像を示しています。 品質を42としてみたところ画質はそこそこなれどディスク
      使用量がもっと小さくなって、 つまりはウェブページでの読み込みが速くなる
      画像ができます。 画質は落ちましたがこの目的に照らせば妥当でしょう。
    </para>
    <figure>
      <title lang="en">Dialog for Image Saving as JPEG</title>
      <title lang="ja">
        画像を<quote><acronym>JPEG</acronym>形式で保存する</quote>ダイアログ
      </title>
      <mediaobject>
        <imageobject>
          <imagedata format="PNG"
            fileref="images/tutorials/quickie-jpeg-dialog2.png"/>
        </imageobject>
      </mediaobject>
    </figure>
    <para lang="en">
      I have not been showing the actual jpegs I created so that we could end
      this quickie with a race.
    </para>
    <para lang="ja">
      私が試してみた<acronym>JPEG</acronym>の実例はまだだったので、
      ここで一挙に比較してみてこの話を締めたいと思います。
    </para>
    <figure>
      <title lang="en">Example for High JPEG Compression</title>
      <title lang="ja"><acronym>JPEG</acronym>高圧縮の例</title>
      <mediaobject>
        <imageobject>
          <imagedata format="PNG"
            fileref="images/tutorials/quickie-jpeg-006.jpg"/>
        </imageobject>
        <caption>
          <para lang="en">Quality: 6; Size: 1361 Bytes</para>
          <para lang="ja">品質: 6; 内容量: 1361 Bytes</para>
        </caption>
      </mediaobject>
      <mediaobject>
        <imageobject>
          <imagedata format="PNG"
            fileref="images/tutorials/quickie-jpeg-042.jpg"/>
        </imageobject>
        <caption>
          <para lang="en">Quality: 42; Size: 3549 Bytes</para>
          <para lang="ja">品質: 42; 内容量: 3549 Bytes</para>
        </caption>
      </mediaobject>
    </figure>
    <figure>
      <title lang="en">Example for Moderate JPEG Compression</title>
      <title lang="ja">中程度の<acronym>JPEG</acronym>圧縮の例</title>
      <mediaobject>
        <imageobject>
          <imagedata format="PNG"
            fileref="images/tutorials/quickie-jpeg-085.jpg"/>
        </imageobject>
        <caption>
          <para lang="en">
            Quality: 85 (<acronym>GIMP<acronym>s default); Size: 6837 Bytes
          </para>
          <para lang="ja">
            品質: 85 (<acronym>GIMP</acronym>初期設定値); 内容量: 6837 Bytes
          </para>
        </caption>
      </mediaobject>
      <mediaobject>
        <imageobject>
          <imagedata format="PNG"
            fileref="images/tutorials/quickie-jpeg-100.jpg"/>
        </imageobject>
        <caption>
          <para lang="en">Quality: 100; Size: 20,971 Bytes</para>
          <para lang="ja">品質: 100; 内容量: 20,971 Bytes</para>
        </caption>
      </mediaobject>
    </figure>
  </sect2>

  <sect2 id="gimp-tutorial-quickie-crop">
    <title lang="en">Crop An Image</title>
    <title lang="ja">画像を切り抜く</title>
    <indexterm lang="en">
      <primary>Tutorial</primary>
    </indexterm>
    <indexterm lang="en">
      <primary>Image</primary>
      <secondary>crop</secondary>
    </indexterm>
    <indexterm lang="ja">
      <primary sortas="エンシュウ">演習</primary>
      </indexterm>
    <indexterm lang="ja">
      <primary sortas="ガゾウ">画像</primary>
      <secondary sortas="キリヌク">切り抜く</secondary>
    </indexterm>
    <figure>
      <title lang="en">Example Image for Cropping</title>
      <title lang="ja">画像切り抜きの例</title>
      <mediaobject>
        <imageobject>
          <imagedata format="JPG"
            fileref="images/tutorials/quickie-crop-example-source.jpg"/>
        </imageobject>
        <caption>
          <para lang="en">Source image</para>
          <para lang="ja">元の画像</para>
        </caption>
      </mediaobject>
      <mediaobject>
        <imageobject>
          <imagedata format="JPG"
            fileref="images/tutorials/quickie-crop-example-result.jpg"/>
        </imageobject>
        <caption>
          <para lang="en">Image after cropping</para>
          <para lang="ja">切り抜いた画像</para>
        </caption>
      </mediaobject>
    </figure>
    <para lang="en">
      There are many reasons to crop an image; for example, fitting an image
      to fill a frame, removing a portion of the background to emphasize the
      subject, etc. There are two methos to activate the crop tool.
      Click the
      <guiicon>
        <inlinemediaobject>
          <imageobject>
            <imagedata fileref="images/toolbox/stock-tool-crop-22.png"/>
          </imageobject>
        </inlinemediaobject>
      </guiicon>
      button in the Toolbox, or use
      <menuchoice>
        <guimenu>Tools</guimenu>
        <guisubmenu>Transform Tools</guisubmenu>
        <guimenuitem>Crop</guimenuitem>
      </menuchoice> in the image window. This will change
      the cursor and allow you to click and drag a rectangular shape. The
      button in the toolbox is the nicest way to get to any of the tools. I
      have chosen one of the huge and beautiful APOD images
      <xref linkend="bibliography-online-apod05"/>.
    </para>
    <para lang="ja">
      画像を切り抜く理由はたくさんあります。 枠に収まるようにしたり、
      背景の要らない部分を切り落として被写体をよく見えるようにしたり...。
      切り抜きツールの呼びだし方には2通りあります。 ツールボックスの 
      <guiicon>
        <inlinemediaobject>
          <imageobject>
            <imagedata fileref="images/toolbox/stock-tool-crop-22.png"/>
          </imageobject>
        </inlinemediaobject>
      </guiicon>
      ボタンをクリックするか、 画像ウィンドウのメニューより
      <menuchoice>
        <guimenu>ツール(<accel>T</accel>)</guimenu>
        <guisubmenu>変換ツール(<accel>T</accel>)</guisubmenu>
        <guimenuitem>切り抜き(<accel>C</accel>)</guimenuitem>
      </menuchoice>
      と進んでください。 するとカーソル形状が換わり、 クリックして曳くことで
      矩形が現れます。 ツールボックスのボタンはツールを手に取るのには最適
      ですね。 ここでは大判で美しい<acronym>APOD</acronym>の画像
      <xref linkend="bibliography-online-apod05" /> を選びました。
    </para>
    <figure>
      <title lang="en">Select a Region to Crop</title>
      <title lang="ja">切り抜き範囲を選択</title>
      <mediaobject>
        <imageobject>
          <imagedata format="JPG"
            fileref="images/tutorials/quickie-crop-step1.png"/>
        </imageobject>
      </mediaobject>
    </figure>
    <para lang="en">
      I always click on the approximate upper left corner and drag to the
      lower right corner; the approximate path is shown in red.
      You don't need to worry about being accurate on this
      first swipe with the crop tool.
    </para>
    <para lang="ja">
      画像を切り抜くとき、 私はおおよその目見当で左上をクリックしてから右下に
      曳いて範囲を決めています。 するとおおよその切り取り線が赤く図示されます。
      切り抜きの最初からきっちり正確にしようと
      苦心する必要はありません。 すぐさまツールオプションでうまく直せます。
    </para>
    <figure>
      <title lang="en">Dialog for Cropping</title>
      <title lang="ja">切り抜きツールオプション</title>
      <mediaobject>
        <imageobject>
          <imagedata format="PNG"
            fileref="images/tutorials/quickie-crop-step2.png"/>
        </imageobject>
      </mediaobject>
    </figure>
    <para lang="en">
      After completing the click and drag motion, a rectangle with special
      regions show the selected area. As the cursor is moved over the
      different areas of the selected crop area, the cursor changes.
      You can then drag the cursor to change the dimensions of the selected
      area. As shown in the figure above, as the crop area is resized,
      the dimensions and ration are shown in the status bar. See
      <xref linkend="gimp-tool-crop"/> for more information on cropping
      in <acronym>GIMP</acronym>. If you would like to make
      this rectangular image square, you should find the width and height from
      the Get Image Information Quickie (see
      <xref linkend="gimp-tutorial-quickie-info"/>. Use the smallest of the
      two lengths to determine the size of the square. In my 300 x 225 pixel
      image, the largest square I can get is 225 x 225 pixels.
      Use the iamge and the
      squares to get the best part of the image for the area.
      Use any of the areas to move the edges and change the dimensions
      to achieve the image that you prefer. Double click in the are
      to crop the image.
    </para>
    <para lang="ja">
      クリックして曳いてボタンを放すと切り抜かれる領域が矩形の枠として画像上に
      図示されます。 この切り抜き枠内や周辺のいろいろなところにマウスをかざすと
      ポインタの姿が変化します。 その各部分をマウスでクリックして曳けば枠の寸法
      や位置が変更できます。 上図で示すとおり、 切り抜き枠の大きさを変えると
      ステータスバーにその寸法が表示されます。 <acronym>GIMP</acronym>の<quote>
      切り抜き</quote>ツールの使い方についてのより詳しい情報は 
      <xref linkend="gimp-tool-crop"/> でご覧ください。 もしこの矩形画像を
      正方形に整形するのならば、 幅と高さの情報を画像情報の早分かり
      <xref linkend="gimp-tutorial-quickie-info" /> 参照) を参考に調べて
      ください。 長方形の短辺で正方形のサイズを決めます。 ここに 300&times;225
      ピクセルの画像があるとして正方形を最大限の大きさで切り抜くとすると、
      225&times;225 ピクセルとなります。 画像の一番良いところを取れるように
      調節することになります。 枠を動かし切り抜く大きさを変え、 望みどおりの
      画像の領域を囲みます。 決まったら枠内中央をクリックすれば切り抜きが実行
      されます。
    </para>
  </sect2>

  <sect2 id="gimp-tutorial-quickie-info">
    <title lang="en">Find Info About Your Image</title>
    <title lang="ja">画像に関する情報を見る</title>
    <indexterm lang="en">
      <primary>Tutorial</primary>
    </indexterm>
    <indexterm lang="en">
      <primary>Image</primary>
      <secondary>information</secondary>
    </indexterm>
    <indexterm lang="ja">
      <primary sortas="エンシュウ">演習</primary>
    </indexterm>
    <indexterm lang="ja">
      <primary sortas="ガゾウ">画像</primary>
      <secondary sortas="ジョウホウ">情報</secondary>
    </indexterm>
    <figure>
      <title lang="en">Finding Info</title>
      <title lang="ja">情報を探る</title>
      <mediaobject>
        <imageobject>
          <imagedata format="JPG"
            fileref="images/tutorials/quickie-info-menu.png"/>
        </imageobject>
      </mediaobject>
    </figure>
    <para lang="en">
      This example uses another image image from APOD
      <xref linkend="bibliography-online-apod06"/>.
      Much information is available directly from the Image Window; for
      example, the image dimensions.Use 
      <menuchoice>
      <guimenu>Image</guimenu>
      <guimenuitem>Image Properties</guimenuitem></menuchoice>
      to open the Image Properties dialog, which contains even more
      information.
    </para>
    <para lang="ja">
      ここでも新たに<acronym>APOD</acronym>
      <xref linkend="bibliography-online-apod06"/> より画像をいただきました。
      画像ウィンドウにはもっと詳しい情報がすぐに得られるしくみがあります。
      例えば画像の寸法もわかります。 画像ウィンドウのメニューより
      <menuchoice>
        <guimenu>画像(<accel>I</accel></guimenu>
        <guimenuitem>画像の情報(<accel>O</accel>)...</guimenuitem>
      </menuchoice>
      と辿ってください。 するとダイアログが現れ、 画像の情報が詳しく書かれて
      います。
    </para>
    <figure>
      <title lang="en">Image Properties Dialog</title>
      <title lang="ja">画像の情報ダイアログ</title>
      <mediaobject>
        <imageobject>
          <imagedata format="PNG"
            fileref="images/tutorials/quickie-info-dialog.png"/>
        </imageobject>
      </mediaobject>
    </figure>
    <para lang="en">
      If you are just making a square out of a rectangle, like in the
      <xref linkend="gimp-tutorial-quickie-crop"/>,
      it is fast and easy to find the smallest dimension.
      You need only to open the dialog and find the lesser length and use
      that as described. Since this is very little information, and definitely
      not enough to fill the space between the menu thumbnail and the dialog
      screenshot in my layout, I thought I would run through some calculator
      exercises that might help you to meet your image needs.
    </para>
   <para lang="ja">
      <xref linkend="gimp-tutorial-quickie-crop" /> のすすめで正方形の画像を
      作っている最中でしたら、 最小の寸法はすぐ簡単に分かるはずです。
      あとはこのダイアログを開いて短辺を読みとり
      再び前の節に戻ってください。 ここでの情報が随分と少ないこともありますが、
      私の画面上ではダイアログのスクリーンショットとメニューの画像の間を
      埋める余裕がなかったので、 ここからときおり計算演習を交じえることに
      なりますが、 理想の画像に近づく一歩だと思ってください。
    </para>
    <figure>
      <title lang="en">Scale Problem</title>
      <title lang="ja">拡大・縮小の問題</title>
      <mediaobject>
        <imageobject>
          <imagedata format="PNG"
            fileref="images/tutorials/quickie-info-problem.png"/>
        </imageobject>
      </mediaobject>
    </figure>
    <para lang="en">
      It is nice to have images appear on a browser window as a photo would.
      Photos online appear to be 4x6 inches when scaled to 288x432 pixels (72
      dpi for many monitors). There is a problem, however, if you try to scale
      this image. The ratio of width to length of the original does not match
      the ratio of the photo. So, to make the scaled image the correct size
      some pixels must be cropped form the height. The final iamge will
      <quote>appear</quote> as a 6x4 inch photo on most monitors.
    </para>
    <para lang="ja">
      ウェブブラウザのウィンドウに写真などの画像が出るのはいいものですね。
      オンラインでの写真を4&times;6インチに見せるには、 (大抵のディスプレイ
      モニタの解像度が72dpiなので) 288&times;432ピクセルの画像にします。 しかし
      ながら画像を縮尺するときに問題がおこります。 原本の縦横比と欲しい写真の
      縦横比が異なっているのです。 そこで縮小した画像の高さを何ピクセルか削って
      適正な大きさにします。 出来上がった画像はほとんどのモニタ上で
      大きさが6&times;4インチの写真に<quote>見える</quote>はずです。
    </para>
    <figure>
      <title lang="en">Problem Solved by Cropping</title>
      <title lang="ja">切り抜きで問題解決</title>
      <mediaobject>
        <imageobject>
          <imagedata format="PNG"
            fileref="images/tutorials/quickie-info-crop.png"/>
        </imageobject>
      </mediaobject>
    </figure>
    <para lang="en">
      There are problems when mixing scanned photos, digital
      photos, and scanned negatives. Modern film developing machines
      automatically crop portions of the image so that they will match
      the printing size, or a certain style.
      If you are preparing an image to be printed on a machine like
      this; or if you are planning on a gallery where the images are from
      different sources, some intelligent cropping to fit the best size for
      the medium you have chosen will be a plus. If this is confusing; please
      blame the photo printing industry and not <acronym>GIMP</acronym>.
    </para>
    <para lang="en">
      You can change the Resolution of your image as well, using the same
      methods as we used to Scale the image, although, in my somewhat limited
      use,
      the issue is more about how many pixels. Let's say you want to print an
      image at a photo lab. 300 pixels for every inch is preferred.
      An image that is 2241x1548 pixels will easily print as
      a 7 x 5 photo. 2241px/300ppi =
      7.47 in. Get your calculator for the short side. 1548/300 = _.
    </para>
    <para lang="en">
      There is another brutal fact you should come to terms with if you are
      new to graphics and computers. Just because it looks good on the screen
      doesn't mean that it will print nicely. I tried to emulate how this
      image would appear printed at 300dpi. Sorry. There are some options, for
      instance my friend printed images and then scanned them back in.
      Terrible business!
    </para>
    <para lang="ja">
      スキャナでとりこんだ写真やデジタル写真やスキャナでとりこんだ写真ネガを
      混ぜて使うと困ったことになります。 近代のフィルムを処理する機械は画像を
      現像紙の大きさかある特定の形式に合わせるため自動的に画像を切り抜きます。
      この種の現像用画像を使うことになっていたり、 あるいは写真展に使う画像の
      出所が異なっているときに、 思い通りのサイズに素材を整える知能切り抜きが
      きっと有利に働くでしょう。 話がややこしかったかもしれませんが写真現像の
      業界の所為ですから、 <acronym>GIMP</acronym>を責めないでください。
    </para>
    <para lang="ja">
      画像を拡大・縮小するときと同じ手順で画像の解像度が変更できますが、
      ちょっと試してみて分かったのがピクセル数をどうするかという問題です。
      ここからは最初の画像を写真館で現像したものと同じにするとの趣向で
      話をすすめます。 1インチあたり300ピクセル[300ppi]がよいでしょう。
      2241&times;1548ピクセルの画像は7&times;5の写真のように印刷するのは簡単
      です。 2241px/300ppi = 7.47 in.
      短辺も計算してみてください。 1548/300 = ??
    </para>
    <para lang="ja">
      グラフィックやコンピュータの初心者にはさらに不都合なことが待っています。
      画面上で見える画像が思ったとおりであっても、 印刷までうまくいくとは
      限らないという問題です。 私は先程、印刷は300dpiだとして画像の見えかたの
      演習をすすめました。 でもごめんなさい。 オプションはいろいろあります。
      私の友人で画像を一旦印刷してスキャナで取り込みなおしたなんて話も
      あるんです。 正直、キツイです。
    </para>
    <figure>
      <title lang="en">Actual printing result of example image</title>
      <title lang="ja">例題画像の実際の印刷結果</title>
      <mediaobject>
        <imageobject>
          <imagedata format="JPG"
            fileref="images/tutorials/quickie-info-print-emul.jpg"/>
        </imageobject>
      </mediaobject>
    </figure>
  </sect2>

  <sect2 id="gimp-tutorial-quickie-change-mode">
    <title lang="en">Change the Mode</title>
    <title lang="ja">モードを変える</title>
    <indexterm lang="en">
      <primary>Tutorial</primary>
    </indexterm>
    <indexterm lang="en">
      <primary>Image</primary>
      <secondary>change Mode</secondary>
    </indexterm>
    <indexterm lang="ja">
      <primary sortas="エンシュウ">演習</primary>
    </indexterm>
    <indexterm lang="ja">
      <primary sortas="ガゾウ">画像</primary>
      <secondary sortas="モードヘンコウ">モード変更</secondary>
    </indexterm>
    <para lang="en">
      As with anything else, images come in different kinds and serve
      different purposes. Sometimes, a small size is important (for web sites)
      and at other times, retaining a high colour depth in all its glory (a
      family portrait) is what you want. <acronym>GIMP</acronym> can handle
      all of this, and
      more, primarily by converting between three fundamental modes, as seen
      in this menu. In order to switch your image to one of these modes, you
      open it and follow that menu and click the mode you want.
    </para>
    <para lang="ja">
      画像に限ったことではありませんが、 手に入れる手段も種類もいろいろ
      ありますし使いかたも様々です。 時には小さなサイズ (ウェブサイト用)
      が必要になることもあれば、 一方でめいっぱいの色数を確保したい
      (家族写真用) ときもあります。 <acronym>GIMP</acronym>はどれでも
      こなせますが、 さらにこのメニューに見えている3つの基本モード間での
      変換もできます。 画像のモードをどれかに切り替えるときは、
      画像を開いてからこのメニューでそのモードをクリックすればいいのです。
    </para>
    <figure>
      <title lang="en">Dialog for changing the mode</title>
      <title lang="ja">モードを変えるメニュー</title>
      <mediaobject>
        <imageobject>
          <imagedata format="PNG"
            fileref="images/tutorials/quickie-mode-menu.png"/>
        </imageobject>
        <caption>
          <para lang="ja">
            宇宙航空研究開発機構(JAXA)/日本放送協会(NHK) 提供の
            <quote>満地球の出</quote>の画像を使用しました。 (訳者)
          </para>
        </caption>
      </mediaobject>
    </figure>
    <para lang="en"><emphasis>RGB</emphasis>
      - This is the default mode, used for high quality rich colour images.
      This is also the mode for most of your image work including
      scaling, cropping, and even flipping, as it gives the computer more
      information to work with. The extra information also makes RGB Mode the
      largest to store as a result.
    </para>
    <para lang="en">
      A little bit of detail if you are interested. Each pixel or point when
      in this mode consists of three different components. R-&gt;Red, G-&gt;Green,
      B-&gt;Blue. Each of these in turn can have an intensity value of 0-255. So,
      at every pixel, what you see is an additive combination of these three
      components. All these combinations result in a way to represent millions
      of colours.
    </para>
<!--
    <para lang="en">
      As an example to practice with images have been provided in various
      sizes and formats. Indexed images of different sizes: from a very old
      APOD a small gif and a larger gif of the same image from a later APOD.
      Also the same image in RGB as provided by Earth Observatory a smaller
      version and a huge version.
    </para>
-->
    <para lang="en"><emphasis>Indexed</emphasis>
      - This is the mode usually used when file size is of concern, or when
      you are working with images with few colours. It involves using a fixed
      number of colours, 256 or less, at each point to represent the colour at
      that point. The defaults to attempting to figure out an "optimum
      palette" to best represent your image. Try it, you can undo it if you
      don't like the results, or use a custom palette or more colours.
    </para>
    <para lang="ja">
      <emphasis>RGB</emphasis>
      - 初期設定でのモードで、 高品質なカラー画像に向いています。 コンピュータ
      により多くの情報量を処理させながら、 画像の拡大・縮小や切り抜き、
      さらには反転など、作業のほとんどを するためのモードでもあります。
      こういった拡張情報があるため<acronym>RGB</acronym>モードは
      結果的に最大容量です。
    </para>
    <para lang="ja">
      少し細かい話をします。 それぞれのピクセル=ポイントはこのモードで3つに
      分解できます: R-&gt;赤、 G-&gt;緑、 B-&gt;青。 このひとつひとつが
      0から255までの強度で表されます。 つまりひとつの画素 (ピクセル) として
      見えているのは3つの要素の合成なのです。
      異なる強度の合成のバリエーションから千数百万の色数がうまれます。
    </para>
    <para lang="ja">
      演習例題でのように画像はさまざまな大きさや形式で提供されています。
      インデックスつき画像の異なる大きさの例: かなり昔の<acronym>APOD</acronym>
      は小さな<acronym>GIF</acronym>がありましたが、 あとで同じ画像が
      より大きな<acronym>GIF</acronym>として出されています。
      Earth Observatory の<acronym>RGB</acronym>画像も
      はじめ小さかったのが同じ画像で大きなものになっています。
    </para>
    <para lang="ja">
      <emphasis>インデックスつき</emphasis>
      - このモードはたいていファイルの容量に気をつけている場合か色数の少ない
      画像で作業しているときに用いられます。 使える色数は256以下の一定数に
      限られており、 そのいずれかの色が各ポイントの色を表します。 初期設定では
      画像を最良に見せる <guilabel>最適パレットを生成</guilabel>が選ばれて
      います。 やってみて結果が気に入らなければ、
      取り消して<guilabel>カスタムパレット</guilabel>を選ぶか
      <guilabel>最大色数(<accel>M</accel>)</guilabel> を増やします。
    </para>
    <figure>
      <title lang="en">Dialog <quote>Change to Indexed Colors</quote></title>
      <title lang="ja"><quote>インデックスカラー変換</quote>ダイアログ</title>
      <mediaobject>
        <imageobject>
          <imagedata format="PNG"
            fileref="images/tutorials/quickie-mode-indexed.png"/>
        </imageobject>
      </mediaobject>
    </figure>
    <para lang="en">
      As you might expect, since the information needed to represent the
      color at each pixel is less, the file size is smaller. However,
      sometimes, there are options in the various menus that are
      "greyed" out for no apparent reason. This usually means that the filter
      or option cannot be applied when your image is in its current mode.
      Changing the mode to RGB, as outlined above, should solve this issue. If
      RGB mode
      doesn't work either, perhaps the option you're trying requires your
      layer to have the ability to be transparent. This can be done just as
      easily via
      <menuchoice>
        <guimenu>Layer</guimenu>
        <guisubmenu>Transparency</guisubmenu>
        <guimenuitem>Add Alpha Channel</guimenuitem>
      </menuchoice>.
    </para>
    <para lang="ja">
      それぞれのピクセルの色を表現するのに必要な情報が少なくなりますから、
      予想どおりファイルの大きさも随分小さくなります。 ところがどういうわけか、
      メニューの一部が数カ所灰色無効になっていることがしばしばあります。
      その理由のほとんどは画像の現在のモードでは適用できないフィルタや
      オプションだからです。 先段で述べた<acronym>RGB</acronym>にモード変換
      すればこの問題は解決するはずです。 そうしてもまだできないときは、
      ひょっとするとそのオプションのためにお使いのレイヤーを透明化可能に
      しなければならないのかもしれません。
      <menuchoice>
        <guimenu>レイヤー(<accel>L</accel>)</guimenu>
        <guisubmenu>透明部分(<accel>A</accel>)</guisubmenu>
        <guimenuitem>アルファチャンネルを追加(<accel>H</accel>)</guimenuitem>
      </menuchoice>
      と進むだけですから簡単です。
    </para>
    <figure>
      <title lang="en">Add Alpha Channel</title>
      <title lang="ja">アルファチャンネルを追加</title>
      <mediaobject>
        <imageobject>
          <imagedata format="PNG"
            fileref="images/tutorials/quickie-mode-alpha.png"/>
        </imageobject>
      </mediaobject>
    </figure>
    <para lang="en"><emphasis>Grayscale</emphasis>
      - In case you want to convert your brilliant colour image to something
      that's black and white (with a lot of shades of grey), this is one of
      the easiest ways in which to do it. Some photos do look a lot fancier
      when displayed in grayscale. Again, if you're interested in some detail,
      this is achieved by taking the RGB values at the pixels in your image,
      and suitably weighted averaging them to get an intensity at that point.
    </para>
    <para lang="en">
      There is no need to convert an image to a specific mode before saving it
      in your favourite format, as <acronym>GIMP</acronym> is smart enough to
      properly export the image.
    </para>
    <para lang="ja">
      <emphasis>グレースケール</emphasis>
      - 鮮かなカラー画像を白黒 (と何階調もの灰色) の画像に変換するときには、 
      グレースケールを使うと簡単にできます。 写真によってはグレースケールに
      すると非常に面白くなります。 また細かい話をしますが、
      これは画像の各ピクセルの<acronym>RGB</acronym>値から
      ちょうどの比重を割り出してその点の強度にしています。
    </para>
    <para lang="ja">
      画像を保存する前にいずれかのモードに変換しておく必要はありません。
      <acronym>GIMP</acronym>はちゃんとしたファイルのエクスポートも颯爽と
      こなします。
    </para>
  </sect2>

  <sect2 id="gimp-tutorial-quickie-flip">
    <title lang="en">Flip An Image</title>
    <title lang="ja">画像を裏返したり反転させる</title>
    <indexterm lang="en">
      <primary>Tutorial</primary>
    </indexterm>
    <indexterm lang="en">
      <primary>Image</primary>
      <secondary>Flip</secondary>
    </indexterm>
    <indexterm lang="ja">
      <primary sortas="エンシュウ">演習</primary>
    </indexterm>
    <indexterm lang="ja">
      <primary sortas="ガゾウ">画像</primary>
      <secondary sortas="ハンテン/ウラガエシ">反転/裏返し</secondary>
    </indexterm>
    <para lang="en">
      When you need the person in the photo looking in the other direction, or
      you need the top of the image to be the bottom. Mirroring the image (sort
      of). Use
      <menuchoice>
        <guimenu>Tools</guimenu>
        <guisubmenu>Transform Tools</guisubmenu>
        <guimenuitem>Flip</guimenuitem>
      </menuchoice>, or use the
      <guiicon>
        <inlinemediaobject>
          <imageobject>
            <imagedata fileref="images/toolbox/stock-tool-flip-22.png" />
          </imageobject>
        </inlinemediaobject>
      </guiicon> button on the toolbox.
    </para>
    <para lang="ja">
      写真に写っている人物の向きを変えたいときや、 画像の上部を底にもって
      ゆきたいときに。 (ある種の) 鏡像。 画像ウィンドウのメニューより
      <menuchoice>
        <guimenu>ツール(<accel>T</accel>)</guimenu>
        <guisubmenu>変換ツール(<accel>T</accel>)</guisubmenu>
        <guimenuitem>鏡像反転(<accel>F</accel>)</guimenuitem>
      </menuchoice>
      と辿るか、 ツールボックスの
      <guiicon>
        <inlinemediaobject>
          <imageobject>
            <imagedata fileref="images/toolbox/stock-tool-flip-22.png" />
          </imageobject>
        </inlinemediaobject>
      </guiicon>
      ボタンで呼び出してください。
    </para>
    <figure>
      <title lang="en">Dialog <quote>Flip an Image</quote></title>
      <title lang="ja">
        メニューより<quote>鏡像反転(<accel>F</accel>)</quote>
      </title>
      <mediaobject>
        <imageobject>
          <imagedata format="PNG"
            fileref="images/tutorials/quickie-flip-menu.png"/>
        </imageobject>
      </mediaobject>
    </figure>
    <para lang="en">
      Using another APOD image <xref linkend="bibliography-online-apod07"/>
      I demonstrated all of the flips on this image.<!-- You might get bored
      before it is over ....-->
    </para>
    <para lang="en"><!-- Changed 2008-08-26 by ciampix -->
      The tool used as is (the default) will simply flip the image at its
      vertical axis. If you double click on the button, the tool options dialog
      will open, if it is not already displayed in the dock under the toolbox.
      Use the options dialog to switch between horizontal and vertical. You
      can also use the
      <keycap>Ctrl</keycap> key to switch between horizontal and vertical.
      All possible flips are displayed in this page.
    </para>
    <para lang="ja">
      他の<acronym>APOD</acronym><xref linkend="bibliography-online-apod07" />
      の画像を用い、その反転のすべてを実演します。
    </para>
    <para lang="ja">
      反転をそのまま (初期設定で) すると画像は縦軸で反転します。 アイコンボタン
      をクリックすれば、 ツールオプションダイアログが現れます。 このツール
      オプションダイアログでも切り替えられますが、 <keycap>Ctrl</keycap> キー
      でも水平と垂直に反転の向きを切り替えられます。
      反転の全ての型をこのページに載せました。
    </para>
    <figure id="quickie-flip-images">
      <title lang="en">Example Image to Flip</title>
      <title lang="ja">鏡像反転の例</title>
      <informalfigure>
        <mediaobject>
          <imageobject>
            <imagedata format="PNG"
              fileref="images/tutorials/quickie-flip-example-source.png"/>
          </imageobject>
          <caption>
            <para lang="en">Source image</para>
            <para lang="ja">元の画像</para>
          </caption>
        </mediaobject>
        <mediaobject>
          <imageobject>
            <imagedata format="PNG"
              fileref="images/tutorials/quickie-flip-example-horizontal.png"/>
          </imageobject>
          <caption>
            <para lang="en">Horizontal flipped image</para>
            <para lang="ja">横軸で反転した画像</para>
          </caption>
        </mediaobject>
      </informalfigure>
      <informalfigure>
        <mediaobject>
          <imageobject>
            <imagedata format="PNG"
              fileref="images/tutorials/quickie-flip-example-vertical.png"/>
          </imageobject>
          <caption>
            <para lang="en">Vertical flipped image</para>
            <para lang="ja">縦軸で反転した画像</para>
          </caption>
        </mediaobject>
        <mediaobject>
          <imageobject>
            <imagedata format="PNG"
              fileref="images/tutorials/quickie-flip-example-horizontal-and-vertical.png"/>
          </imageobject>
          <caption>
            <para lang="en">Horizontal and vertical flipped image</para>
            <para lang="ja">縦軸と横軸それぞれに反転した画像</para>
          </caption>
        </mediaobject>
      </informalfigure>
    </figure>
  </sect2>

  <sect2 id="gimp-tutorial-quickie-rotate">
    <title lang="en">Rotate An Image</title>
    <title lang="ja">画像を回転させる</title>
    <indexterm lang="en">
      <primary>Tutorial</primary>
    </indexterm>
    <indexterm lang="en">
      <primary>Image</primary>
      <secondary>Rotate</secondary>
    </indexterm>
    <indexterm lang="ja">
      <primary sortas="エンシュウ">演習</primary>
    </indexterm>
    <indexterm lang="ja">
      <primary sortas="ガゾウ">画像</primary>
      <secondary sortas="カイテン">回転</secondary>
    </indexterm>
    <figure>
      <title lang="en">Menu for <quote>Rotate An Image</quote></title>
      <title lang="ja">画像の<quote>回転</quote>メニュー</title>
      <mediaobject>
        <imageobject>
          <imagedata format="PNG"
            fileref="images/tutorials/quickie-rotate-menu.png"/>
        </imageobject>
      </mediaobject>
    </figure>
    <para lang="en">
      Let's say you turned your brand new digital camera to get a vertical shot,
      now some of your images are on their sides. Use
      <menuchoice>
        <guimenu>Image</guimenu>
        <guisubmenu>Transforms</guisubmenu>
        <guimenuitem>Rotate 90° clockwise</guimenuitem>
      </menuchoice>.
      Using an APOD image. I rotated it once to demonstrate 90 degrees CCW.
    </para>
    <para lang="ja">
      新型のデジタルカメラを縦に構えて写真を撮ったところ、 横倒しの画像になって
      しまいました&hellip;。 そんなときには画像ウィンドウのメニューより
      <menuchoice>
        <guimenu>画像(<accel>I</accel>)</guimenu>
        <guisubmenu>変換(<accel>T</accel>)</guisubmenu>
        <guimenuitem>時計回りに 90 度回転(<accel>C</accel>)</guimenuitem>
      </menuchoice>
      と進みましょう。 <acronym>APOD</acronym>の画像を使います。
      実演のため <guilabel>反時計回りに 90 度回転(<accel>w</accel>)</guilabel>
      も実行しました。
    </para>
    <figure>
      <title lang="en">Example for <quote>Rotate An Image</quote></title>
      <title lang="ja">画像の<quote>回転</quote>の例</title>
      <mediaobject>
        <imageobject>
          <imagedata format="PNG"
            fileref="images/tutorials/quickie-rotate-example-source.png"/>
        </imageobject>
        <caption>
          <para lang="en">Source Image</para>
          <para lang="ja">元の画像</para>
        </caption>
      </mediaobject>
      <mediaobject>
        <imageobject>
          <imagedata format="PNG"
            fileref="images/tutorials/quickie-rotate-example-90-CCW.png"/>
        </imageobject>
        <caption>
          <para lang="en">Rotated image 90 degree CCW</para>
          <para lang="ja">反時計回りに 90 度回転</para>
        </caption>
      </mediaobject>
    </figure>
  </sect2>
</sect1>
